{
    "apps":[
        {
            "title": "Geoffrey and the Dragon Spear",
            "link":"https://muggyfox1.itch.io/geoffrey-and-the-dragon-spear",
            "img":"https://img.itch.zone/aW1nLzQwMDI5NDQucG5n/315x250%23c/VPkGST.png",
            "date": "7/10/2024"
        },
        {
            "title": "Kids Quote Book",
            "link":"https://muggyfox1.itch.io/kids-quote-book",
            "img":"assets/kids quote book feature graphic.png",
            "date": "9/4/2024"
        },
        {
            "title": "The start of an adventure (GameJam)",
            "link": "https://muggyfox1.itch.io/the-start-of-an-adventure",
            "img": "https://img.itch.zone/aW1hZ2UvMzMyNTM3MC8xOTg1NTc0NS5wbmc=/original/LMWtMP.png",
            "date": "02/14/2025"
        }
    ]
}